{
  "updated_at": "2026-04-24 18:13",
  "update_frequency": "Hafta ici her gun 10:01, 12:30, 17:00 ve 19:30'da otomatik guncellenir. Admin manuel olarak istedigi zaman yenileyebilir.",
  "total_assets": 4,
  "signal_counts": {
    "STRONG_BUY": 0,
    "BUY": 1,
    "WEAK_BUY": 0,
    "HOLD": 3,
    "WEAK_SELL": 0,
    "SELL": 0,
    "STRONG_SELL": 0
  },
  "assets": [
    {
      "ticker": "GC=F",
      "name": "Altın (Ons)",
      "sector": "Emtia",
      "price": 4740.8999,
      "change_pct": 0.7609,
      "rsi": 48.7677,
      "stoch_k": 48.9142,
      "adx": 30.4689,
      "volume_ratio": 8.8,
      "signal": "AL",
      "signal_en": "BUY",
      "score": 34.2,
      "confidence": 84.3,
      "color": "#00c853",
      "targets": {
        "target_1": 5018.78,
        "target_2": 5235.65,
        "target_3": 5517.8,
        "stop_loss": 4649.26,
        "add_level": 4704.24
      },
      "range_3m": {
        "min": 4100.8,
        "max": 5586.2
      },
      "range_6m": {
        "min": 3913.7,
        "max": 5586.2
      },
      "explanation_short": "🟢 Günlük bazda ALIŞ sinyali veriyoruz. Alım sebepleri: AL — Güçlü yükseliş momentumu devam ediyor. | HAFİF AL — Genel trend yukarı yönlü. | GÜÇLÜ AL — Kurumsal alım sinyali! Dev hacim + yükseliş.. ⚠️ ",
      "price_try": 6862.15,
      "tl_info": "Gram TL: ₺6,862.15"
    },
    {
      "ticker": "SI=F",
      "name": "Gümüş (Ons)",
      "sector": "Emtia",
      "price": 75.77,
      "change_pct": 0.4042,
      "rsi": 47.7058,
      "stoch_k": 44.9727,
      "adx": 15.5391,
      "volume_ratio": 18.1,
      "signal": "BEKLE",
      "signal_en": "HOLD",
      "score": 15.0,
      "confidence": 47.3,
      "color": "#ffd740",
      "targets": {
        "target_1": 84.09,
        "target_2": 86.05,
        "target_3": 91.2,
        "stop_loss": 73.67,
        "add_level": 74.93
      },
      "range_3m": {
        "min": 61.09,
        "max": 121.3
      },
      "range_6m": {
        "min": 45.85,
        "max": 121.3
      },
      "explanation_short": "🟡 Günlük bazda BEKLEME sinyali veriyoruz. Göstergeler karışık sinyal üretiyor. \n\n📊 DESTEK & DİRENÇ SEVİYELERİ:\n  • Direnç 3: ₺171.23\n  • Direnç 2: ₺146.26\n  • Direnç 1: ₺111.02\n  • Pivot: ₺86.05\n  • D",
      "price_try": 109.67,
      "tl_info": "Gram TL: ₺109.67"
    },
    {
      "ticker": "BTC-USD",
      "name": "Bitcoin",
      "sector": "Kripto",
      "price": 77744.3594,
      "change_pct": -0.6702,
      "rsi": 63.4033,
      "stoch_k": 80.6928,
      "adx": 44.7611,
      "volume_ratio": 0.9,
      "signal": "BEKLE",
      "signal_en": "HOLD",
      "score": -1.2,
      "confidence": 2.7,
      "color": "#ffd740",
      "targets": {
        "target_1": 73255.18,
        "target_2": 72136.14,
        "target_3": 71010.59,
        "stop_loss": 79778.98,
        "add_level": 78558.21
      },
      "range_3m": {
        "min": 62553.19,
        "max": 79468.0
      },
      "range_6m": {
        "min": 60074.2,
        "max": 97860.6
      },
      "explanation_short": "🟡 Günlük bazda BEKLEME sinyali veriyoruz. Göstergeler karışık sinyal üretiyor. \n\n📊 DESTEK & DİRENÇ SEVİYELERİ:\n  • Direnç 3: ₺100871.99\n  • Direnç 2: ₺90169.99\n  • Direnç 1: ₺83957.18\n  • Pivot: ₺7325",
      "price_try": 3500074.52,
      "tl_info": "₺3,500,075"
    },
    {
      "ticker": "ETH-USD",
      "name": "Ethereum",
      "sector": "Kripto",
      "price": 2308.73,
      "change_pct": -0.9772,
      "rsi": 54.0046,
      "stoch_k": 45.9009,
      "adx": 46.6707,
      "volume_ratio": 0.8,
      "signal": "BEKLE",
      "signal_en": "HOLD",
      "score": -7.1,
      "confidence": 22.3,
      "color": "#ffd740",
      "targets": {
        "target_1": 2212.41,
        "target_2": 2192.54,
        "target_3": 2134.45,
        "stop_loss": 2318.1,
        "add_level": 2319.81
      },
      "range_3m": {
        "min": 1804.11,
        "max": 2464.78
      },
      "range_6m": {
        "min": 1748.63,
        "max": 3397.9
      },
      "explanation_short": "🟡 Günlük bazda BEKLEME sinyali veriyoruz. Göstergeler karışık sinyal üretiyor. \n\n📊 DESTEK & DİRENÇ SEVİYELERİ:\n  • Direnç 3: ₺3241.64\n  • Direnç 2: ₺2853.21\n  • Direnç 1: ₺2580.97\n  • Pivot: ₺2192.54\n",
      "price_try": 103939.72,
      "tl_info": "₺103,940"
    }
  ]
}