{
  "updated_at": "2026-03-12 13:18",
  "update_frequency": "Borsa saatleri içerisinde her saat başı otomatik güncellenir",
  "bist30": {
    "index_value": 15211.45,
    "change_percent": 1.25,
    "volume": 0,
    "high": 15292.87,
    "low": 14945.91,
    "date": "2026-03-12"
  },
  "indices": {
    "XU030": {
      "name": "BIST 30",
      "ticker": "XU030.IS",
      "value": 15211.45,
      "change": 187.95,
      "change_pct": 1.25,
      "weekly_change_pct": 4.68,
      "monthly_change_pct": 0.76,
      "yearly_high": 16014.0,
      "yearly_low": 9733.6,
      "volume": 0,
      "sma20": 15255.2,
      "sma50": 14609.38,
      "sma200": 12437.04,
      "trend": "YÜKSELEN",
      "trend_color": "#69f0ae",
      "yorum": "BIST 30 yükseliş eğiliminde. Orta vadeli ortalama olan SMA50'nin üzerinde seyrediyor. Kısa vadeli çekilmeler alım fırsatı olabilir.",
      "gunluk_yorum": "Bugün piyasa pozitif seyrediyor. Alıcılar ağırlıkta, olumlu hava devam ediyor."
    },
    "XU100": {
      "name": "BIST 100",
      "ticker": "XU100.IS",
      "value": 13388.68,
      "change": 188.28,
      "change_pct": 1.43,
      "weekly_change_pct": 4.66,
      "monthly_change_pct": -2.89,
      "yearly_high": 14532.7,
      "yearly_low": 8872.75,
      "volume": 0,
      "sma20": 13591.28,
      "sma50": 13221.85,
      "sma200": 11295.32,
      "trend": "YÜKSELEN",
      "trend_color": "#69f0ae",
      "yorum": "BIST 100 yükseliş eğiliminde. Orta vadeli ortalama olan SMA50'nin üzerinde seyrediyor. Kısa vadeli çekilmeler alım fırsatı olabilir.",
      "gunluk_yorum": "Bugün piyasa pozitif seyrediyor. Alıcılar ağırlıkta, olumlu hava devam ediyor."
    }
  },
  "top_buys": [
    {
      "ticker": "ASELS",
      "name": "Aselsan",
      "sector": "Savunma",
      "price": 332.5,
      "change_pct": -0.968,
      "rsi": 57.5146,
      "stoch_k": 62.1622,
      "adx": 46.4416,
      "volume_ratio": 0.4,
      "signal": "HAFİF AL",
      "signal_en": "WEAK_BUY",
      "score": 23.4,
      "confidence": 65.4,
      "color": "#69f0ae",
      "targets": {
        "target_1": 337.49,
        "target_2": 342.48,
        "target_3": 347.46,
        "stop_loss": 325.85,
        "add_level": 329.18
      },
      "explanation_short": "🟢 Günlük bazda ALIŞ sinyali veriyoruz. Alım sebepleri: HAFİF AL — Yükseliş trendi sürüyor ama momentum azalıyor. | AL — Tüm ortalamalar altında, mükemmel teknik görünüm. | AL — Altın kesişim aktif. Uz"
    },
    {
      "ticker": "TUPRS",
      "name": "Tüpraş",
      "sector": "Enerji",
      "price": 262.25,
      "change_pct": 5.6182,
      "rsi": 69.7989,
      "stoch_k": 76.834,
      "adx": 33.4992,
      "volume_ratio": 0.9,
      "signal": "HAFİF AL",
      "signal_en": "WEAK_BUY",
      "score": 19.5,
      "confidence": 39.6,
      "color": "#69f0ae",
      "targets": {
        "target_1": 266.18,
        "target_2": 270.12,
        "target_3": 274.05,
        "stop_loss": 257.0,
        "add_level": 259.63
      },
      "explanation_short": "🟡 Günlük bazda BEKLEME sinyali veriyoruz. Göstergeler karışık sinyal üretiyor. \n\n📊 DESTEK & DİRENÇ SEVİYELERİ:\n  • Direnç 3: ₺393.72\n  • Direnç 2: ₺335.48\n  • Direnç 1: ₺298.87\n  • Pivot: ₺240.63\n  • "
    },
    {
      "ticker": "ODAS",
      "name": "Odaş Elektrik",
      "sector": "Enerji",
      "price": 6.28,
      "change_pct": 4.6667,
      "rsi": 62.2204,
      "stoch_k": 82.6531,
      "adx": 19.3099,
      "volume_ratio": 0.9,
      "signal": "HAFİF AL",
      "signal_en": "WEAK_BUY",
      "score": 15.9,
      "confidence": 30.5,
      "color": "#69f0ae",
      "targets": {
        "target_1": 6.37,
        "target_2": 6.47,
        "target_3": 6.56,
        "stop_loss": 6.15,
        "add_level": 6.22
      },
      "explanation_short": "🟡 Günlük bazda BEKLEME sinyali veriyoruz. Göstergeler karışık sinyal üretiyor. \n\n📊 DESTEK & DİRENÇ SEVİYELERİ:\n  • Direnç 3: ₺8.43\n  • Direnç 2: ₺7.50\n  • Direnç 1: ₺6.89\n  • Pivot: ₺5.96\n  • Destek 1"
    },
    {
      "ticker": "TKFEN",
      "name": "Tekfen Holding",
      "sector": "Holding",
      "price": 85.85,
      "change_pct": 1.4176,
      "rsi": 60.923,
      "stoch_k": 91.9512,
      "adx": 30.2136,
      "volume_ratio": 0.8,
      "signal": "HAFİF AL",
      "signal_en": "WEAK_BUY",
      "score": 13.5,
      "confidence": 34.0,
      "color": "#69f0ae",
      "targets": {
        "target_1": 87.14,
        "target_2": 88.43,
        "target_3": 89.71,
        "stop_loss": 84.13,
        "add_level": 84.99
      },
      "explanation_short": "🟡 Günlük bazda BEKLEME sinyali veriyoruz. Göstergeler karışık sinyal üretiyor. \n\n📊 DESTEK & DİRENÇ SEVİYELERİ:\n  • Direnç 3: ₺127.48\n  • Direnç 2: ₺111.62\n  • Direnç 1: ₺98.73\n  • Pivot: ₺82.87\n  • De"
    }
  ],
  "top_sells": [
    {
      "ticker": "GARAN",
      "name": "Garanti BBVA",
      "sector": "Bankacılık",
      "price": 139.1,
      "change_pct": -0.1436,
      "rsi": 38.8174,
      "stoch_k": 27.2727,
      "adx": 30.9373,
      "volume_ratio": 0.6,
      "signal": "HAFİF SAT",
      "signal_en": "WEAK_SELL",
      "score": -21.7,
      "confidence": 55.5,
      "color": "#ff8a80",
      "targets": {
        "target_1": 137.01,
        "target_2": 134.93,
        "target_3": 132.84,
        "stop_loss": 141.88,
        "add_level": 140.49
      },
      "explanation_short": "🔴 Günlük bazda SATIŞ sinyali veriyoruz. Satış sebepleri: HAFİF SAT — Düşüş trendi var ama zayıflıyor. | SAT — Tüm ortalamalar üstünde, ağır düşüş trendi. | HAFİF SAT — Kısa vadeli düşüş baskısı var.. "
    },
    {
      "ticker": "HEKTS",
      "name": "Hektaş",
      "sector": "Kimya",
      "price": 3.07,
      "change_pct": 5.8621,
      "rsi": 49.351,
      "stoch_k": 49.1803,
      "adx": 35.8026,
      "volume_ratio": 1.9,
      "signal": "HAFİF SAT",
      "signal_en": "WEAK_SELL",
      "score": -21.4,
      "confidence": 56.6,
      "color": "#ff8a80",
      "targets": {
        "target_1": 3.02,
        "target_2": 2.98,
        "target_3": 2.93,
        "stop_loss": 3.13,
        "add_level": 3.1
      },
      "explanation_short": "🔴 Günlük bazda SATIŞ sinyali veriyoruz. Satış sebepleri: HAFİF SAT — Düşüş trendi var ama zayıflıyor. | SAT — Tüm ortalamalar üstünde, ağır düşüş trendi. | SAT — Ölüm kesişimi aktif. Uzun vadeli düşüş"
    },
    {
      "ticker": "PGSUS",
      "name": "Pegasus",
      "sector": "Havacılık",
      "price": 180.3,
      "change_pct": 0.1667,
      "rsi": 35.4401,
      "stoch_k": 31.6302,
      "adx": 31.0642,
      "volume_ratio": 0.4,
      "signal": "HAFİF SAT",
      "signal_en": "WEAK_SELL",
      "score": -20.9,
      "confidence": 54.6,
      "color": "#ff8a80",
      "targets": {
        "target_1": 177.6,
        "target_2": 174.89,
        "target_3": 172.19,
        "stop_loss": 183.91,
        "add_level": 182.1
      },
      "explanation_short": "🔴 Günlük bazda SATIŞ sinyali veriyoruz. Satış sebepleri: HAFİF SAT — Düşüş trendi var ama zayıflıyor. | SAT — Tüm ortalamalar üstünde, ağır düşüş trendi. | SAT — Ölüm kesişimi aktif. Uzun vadeli düşüş"
    },
    {
      "ticker": "TAVHL",
      "name": "TAV Havalimanları",
      "sector": "Havacılık",
      "price": 304.25,
      "change_pct": 0.5785,
      "rsi": 42.7527,
      "stoch_k": 44.9153,
      "adx": 57.9954,
      "volume_ratio": 0.5,
      "signal": "HAFİF SAT",
      "signal_en": "WEAK_SELL",
      "score": -16.4,
      "confidence": 66.1,
      "color": "#ff8a80",
      "targets": {
        "target_1": 299.69,
        "target_2": 295.12,
        "target_3": 290.56,
        "stop_loss": 310.33,
        "add_level": 307.29
      },
      "explanation_short": "🟡 Günlük bazda BEKLEME sinyali veriyoruz. Göstergeler karışık sinyal üretiyor. \n\n📊 DESTEK & DİRENÇ SEVİYELERİ:\n  • Direnç 3: ₺447.50\n  • Direnç 2: ₺408.25\n  • Direnç 1: ₺356.25\n  • Pivot: ₺317.00\n  • "
    },
    {
      "ticker": "BIMAS",
      "name": "BİM",
      "sector": "Perakende",
      "price": 712.0,
      "change_pct": 2.5198,
      "rsi": 62.2898,
      "stoch_k": 92.0705,
      "adx": 41.5551,
      "volume_ratio": 1.1,
      "signal": "HAFİF SAT",
      "signal_en": "WEAK_SELL",
      "score": -15.7,
      "confidence": 32.9,
      "color": "#ff8a80",
      "targets": {
        "target_1": 701.32,
        "target_2": 690.64,
        "target_3": 679.96,
        "stop_loss": 726.24,
        "add_level": 719.12
      },
      "explanation_short": "🟡 Günlük bazda BEKLEME sinyali veriyoruz. Göstergeler karışık sinyal üretiyor. \n\n📊 DESTEK & DİRENÇ SEVİYELERİ:\n  • Direnç 3: ₺980.17\n  • Direnç 2: ₺852.33\n  • Direnç 1: ₺782.17\n  • Pivot: ₺654.33\n  • "
    }
  ],
  "signal_counts": {
    "STRONG_BUY": 0,
    "BUY": 0,
    "WEAK_BUY": 4,
    "HOLD": 9,
    "WEAK_SELL": 15,
    "SELL": 0,
    "STRONG_SELL": 0
  },
  "news": [
    {
      "title": "📊 BIST 30 Teknik Analiz Raporu Güncellendi",
      "summary": "Tüm BIST 30 hisseleri için güncel teknik analiz raporu hazırlandı. 12.03.2026 13:18 itibarıyla 9 farklı gösterge ile analiz yapıldı.",
      "date": "12.03.2026 13:18",
      "category": "analiz",
      "icon": "📊"
    },
    {
      "title": "🔔 Stochastic & ADX Göstergeleri Eklendi",
      "summary": "Yeni teknik göstergeler: Stochastic Oscillator ve ADX (Average Directional Index) artık tüm hisseler için hesaplanıyor. Fibonacci düzeltme seviyeleri de aktif.",
      "date": "12.03.2026 13:18",
      "category": "güncelleme",
      "icon": "🔔"
    },
    {
      "title": "🎯 Hedef Fiyat Sistemi Aktif",
      "summary": "Her hisse için günlük, haftalık ve aylık hedef fiyatlar, stop-loss seviyeleri ve ekleme noktaları hesaplanıyor.",
      "date": "12.03.2026 13:18",
      "category": "özellik",
      "icon": "🎯"
    },
    {
      "title": "⏰ Veriler Borsa Saatlerinde Saatlik Güncelleniyor",
      "summary": "Piyasa açıkken (10:00 - 18:30) veriler her saat başı otomatik güncellenir. Son güncelleme saatini sayfanın üstünde görebilirsiniz.",
      "date": "12.03.2026",
      "category": "bilgi",
      "icon": "⏰"
    }
  ]
}